comparative.py
comparative-0.0.2.dist-info/LICENSE
comparative-0.0.2.dist-info/METADATA
comparative-0.0.2.dist-info/WHEEL
comparative-0.0.2.dist-info/top_level.txt
comparative-0.0.2.dist-info/RECORD
