Metadata-Version: 2.1
Name: comparative
Version: 0.0.2
Summary: Implement comparison magic methods in one line!
Home-page: https://github.com/ebukari/comparative
Author: Ezekiel Naa Bukari
Author-email: enbukari@gmail.com
License: UNKNOWN
Platform: UNKNOWN
Classifier: Programming Language :: Python :: 3
Classifier: Programming Language :: Python :: 2
Classifier: License :: OSI Approved :: MIT License
Classifier: Operating System :: OS Independent
